AUTHORS
LICENSE
MANIFEST.in
README.rst
setup.py
django_hvad.egg-info/PKG-INFO
django_hvad.egg-info/SOURCES.txt
django_hvad.egg-info/dependency_links.txt
django_hvad.egg-info/not-zip-safe
django_hvad.egg-info/requires.txt
django_hvad.egg-info/top_level.txt
docs/Makefile
docs/conf.py
docs/glossary.rst
docs/index.rst
docs/make.bat
docs/_ext/djangodocs.py
docs/_ext/github.py
docs/_static/.gitignore
docs/_static/stylesheet.css
docs/internal/admin.rst
docs/internal/descriptors.rst
docs/internal/exceptions.rst
docs/internal/fieldtranslator.rst
docs/internal/forms.rst
docs/internal/general.rst
docs/internal/index.rst
docs/internal/manager.rst
docs/internal/models.rst
docs/internal/query.rst
docs/internal/utils.rst
docs/public/admin.rst
docs/public/contact.rst
docs/public/contributing.rst
docs/public/faq.rst
docs/public/forms.rst
docs/public/installation.rst
docs/public/models.rst
docs/public/queryset.rst
docs/public/quickstart.rst
docs/public/release_notes.rst
docs/public/restframework.rst
hvad/__init__.py
hvad/admin.py
hvad/compat.py
hvad/descriptors.py
hvad/exceptions.py
hvad/forms.py
hvad/manager.py
hvad/models.py
hvad/query.py
hvad/utils.py
hvad/views.py
hvad/contrib/__init__.py
hvad/contrib/restframework/__init__.py
hvad/contrib/restframework/serializers.py
hvad/contrib/restframework/utils.py
hvad/locale/en/LC_MESSAGES/django.mo
hvad/locale/en/LC_MESSAGES/django.po
hvad/locale/fr/LC_MESSAGES/django.mo
hvad/locale/fr/LC_MESSAGES/django.po
hvad/locale/it/LC_MESSAGES/django.mo
hvad/locale/it/LC_MESSAGES/django.po
hvad/locale/lv/LC_MESSAGES/django.mo
hvad/locale/lv/LC_MESSAGES/django.po
hvad/locale/ru/LC_MESSAGES/django.mo
hvad/locale/ru/LC_MESSAGES/django.po
hvad/templates/admin/hvad/change_form.html
hvad/templates/admin/hvad/deletion_not_allowed.html
hvad/templates/admin/hvad/edit_inline/stacked.html
hvad/templates/admin/hvad/edit_inline/tabular.html
hvad/templates/admin/hvad/includes/translation_tabs.html
hvad/test_utils/__init__.py
hvad/test_utils/cli.py
hvad/test_utils/context_managers.py
hvad/test_utils/data.py
hvad/test_utils/dj_database_url.py
hvad/test_utils/fixtures.py
hvad/test_utils/forms.py
hvad/test_utils/runners.py
hvad/test_utils/testcase.py
