Metadata-Version: 1.1
Name: django-hvad
Version: 1.7.0
Summary: A content translation framework for django integrated automatically in the normal ORM. Removes the pain of having to think about translations in a django project.
Home-page: https://github.com/KristianOellegaard/django-hvad
Author: Kristian Ollegaard
Author-email: kristian.ollegaard@divio.ch
License: UNKNOWN
Platform: UNKNOWN
Classifier: Development Status :: 5 - Production/Stable
Classifier: Framework :: Django
Classifier: Intended Audience :: Developers
Classifier: License :: OSI Approved :: BSD License
Classifier: Operating System :: OS Independent
Classifier: Programming Language :: Python :: 2.7
Classifier: Programming Language :: Python :: 3.3
Classifier: Programming Language :: Python :: 3.4
Classifier: Programming Language :: Python :: 3.5
Classifier: Topic :: Database
Classifier: Topic :: Internet :: WWW/HTTP :: Dynamic Content
Classifier: Topic :: Text Processing :: Linguistic
